ugTranslate/__init__.py
ugTranslate/main.py
UGTranslate-0.4.dist-info/METADATA
UGTranslate-0.4.dist-info/WHEEL
UGTranslate-0.4.dist-info/entry_points.txt
UGTranslate-0.4.dist-info/top_level.txt
UGTranslate-0.4.dist-info/RECORD
