Metadata-Version: 2.1
Name: UGTranslate
Version: 0.4
Summary: A lightweight package for translating text between languages, similar to Google Translate, with simple API integration and easy-to-use functions.
Author: Siraj Dal
Author-email: siraj.d.actowiz@gmail.com
Requires-Python: >=3.6
Requires-Dist: requests
Requires-Dist: unidecode
